{"sections":[],"topicSections":[{"title":"Value Type Protocol","identifiers":["doc:\/\/SwiftPList\/documentation\/SwiftPList\/PListValue"],"anchor":"Value-Type-Protocol"},{"title":"Type Aliases","identifiers":["doc:\/\/SwiftPList\/documentation\/SwiftPList\/PListDictionary","doc:\/\/SwiftPList\/documentation\/SwiftPList\/PListArray"],"anchor":"Type-Aliases"}],"primaryContentSections":[{"kind":"content","content":[{"type":"heading","text":"Overview","anchor":"Overview","level":2},{"type":"paragraph","inlineContent":[{"isActive":true,"type":"reference","identifier":"https:\/\/developer.apple.com\/library\/archive\/documentation\/Cocoa\/Conceptual\/PropertyLists\/AboutPropertyLists\/AboutPropertyLists.html"},{"text":" have a specific set of allowable value types when dealing directly with ","type":"text"},{"type":"codeVoice","code":"PropertyListSerialization"},{"text":":","type":"text"}]},{"type":"table","header":"row","rows":[[[{"type":"paragraph","inlineContent":[{"type":"text","text":"Abstract Type"}]}],[{"inlineContent":[{"text":"XML element","type":"text"}],"type":"paragraph"}],[{"inlineContent":[{"type":"text","text":"Cocoa class"}],"type":"paragraph"}],[{"inlineContent":[{"type":"text","text":"Core Foundation type"}],"type":"paragraph"}]],[[{"inlineContent":[{"type":"text","text":"array"}],"type":"paragraph"}],[{"inlineContent":[{"code":"<array>","type":"codeVoice"}],"type":"paragraph"}],[{"inlineContent":[{"type":"codeVoice","code":"NSArray"}],"type":"paragraph"}],[{"inlineContent":[{"code":"CFArray","type":"codeVoice"}],"type":"paragraph"}]],[[{"inlineContent":[{"type":"text","text":"dictionary"}],"type":"paragraph"}],[{"inlineContent":[{"code":"<dict>","type":"codeVoice"}],"type":"paragraph"}],[{"inlineContent":[{"type":"codeVoice","code":"NSDictionary"}],"type":"paragraph"}],[{"inlineContent":[{"type":"codeVoice","code":"CFDictionary"}],"type":"paragraph"}]],[[{"inlineContent":[{"text":"string","type":"text"}],"type":"paragraph"}],[{"inlineContent":[{"type":"codeVoice","code":"<string>"}],"type":"paragraph"}],[{"type":"paragraph","inlineContent":[{"type":"codeVoice","code":"NSString"}]}],[{"type":"paragraph","inlineContent":[{"type":"codeVoice","code":"CFString"}]}]],[[{"type":"paragraph","inlineContent":[{"type":"text","text":"data"}]}],[{"type":"paragraph","inlineContent":[{"type":"codeVoice","code":"<data>"}]}],[{"type":"paragraph","inlineContent":[{"code":"NSData","type":"codeVoice"}]}],[{"type":"paragraph","inlineContent":[{"type":"codeVoice","code":"CFData"}]}]],[[{"type":"paragraph","inlineContent":[{"text":"date","type":"text"}]}],[{"type":"paragraph","inlineContent":[{"code":"<date>","type":"codeVoice"}]}],[{"type":"paragraph","inlineContent":[{"type":"codeVoice","code":"NSDate"}]}],[{"type":"paragraph","inlineContent":[{"type":"codeVoice","code":"CFDate"}]}]],[[{"type":"paragraph","inlineContent":[{"type":"text","text":"integer"}]}],[{"type":"paragraph","inlineContent":[{"type":"codeVoice","code":"<integer>"}]}],[{"type":"paragraph","inlineContent":[{"type":"codeVoice","code":"NSNumber"},{"type":"text","text":" ("},{"type":"codeVoice","code":"intValue"},{"type":"text","text":")"}]}],[{"type":"paragraph","inlineContent":[{"type":"codeVoice","code":"CFNumber"},{"type":"text","text":", integer"}]}]],[[{"type":"paragraph","inlineContent":[{"type":"text","text":"float"}]}],[{"type":"paragraph","inlineContent":[{"code":"<real>","type":"codeVoice"}]}],[{"type":"paragraph","inlineContent":[{"type":"codeVoice","code":"NSNumber"},{"text":" (","type":"text"},{"type":"codeVoice","code":"floatValue"},{"text":")","type":"text"}]}],[{"type":"paragraph","inlineContent":[{"code":"CFNumber","type":"codeVoice"},{"type":"text","text":", floating-point"}]}]],[[{"type":"paragraph","inlineContent":[{"text":"boolean","type":"text"}]}],[{"type":"paragraph","inlineContent":[{"code":"<true\/>","type":"codeVoice"},{"text":" or ","type":"text"},{"code":"<false\/>","type":"codeVoice"}]}],[{"type":"paragraph","inlineContent":[{"code":"NSNumber","type":"codeVoice"},{"type":"text","text":" "},{"code":"boolValue","type":"codeVoice"}]}],[{"type":"paragraph","inlineContent":[{"type":"codeVoice","code":"CFBoolean"}]}]]]},{"inlineContent":[{"type":"text","text":"The "},{"type":"reference","isActive":true,"identifier":"doc:\/\/SwiftPList\/documentation\/SwiftPList\/PList"},{"type":"text","text":" class uses Swift-native value types instead and seamlessly translates them to\/from the "},{"type":"codeVoice","code":"PropertyListSerialization"},{"type":"text","text":" types for you when loading or saving the plist to disk."}],"type":"paragraph"},{"inlineContent":[{"text":"These all conform to the ","type":"text"},{"identifier":"doc:\/\/SwiftPList\/documentation\/SwiftPList\/PListValue","isActive":true,"type":"reference"},{"text":" protocol which allows any of them to be nested within dictionaries or arrays while ensuring type safety by preventing invalid types:","type":"text"}],"type":"paragraph"},{"header":"row","rows":[[[{"inlineContent":[{"text":"Abstract Type","type":"text"}],"type":"paragraph"}],[{"inlineContent":[{"text":"swift-plist Swift Type","type":"text"}],"type":"paragraph"}],[{"inlineContent":[{"type":"text","text":"Typealias"}],"type":"paragraph"}]],[[{"inlineContent":[{"text":"array","type":"text"}],"type":"paragraph"}],[{"inlineContent":[{"type":"codeVoice","code":"["},{"text":" ","type":"text"},{"identifier":"doc:\/\/SwiftPList\/documentation\/SwiftPList\/PListValue","isActive":true,"type":"reference"},{"text":" ","type":"text"},{"type":"codeVoice","code":"]"}],"type":"paragraph"}],[{"inlineContent":[{"isActive":true,"type":"reference","identifier":"doc:\/\/SwiftPList\/documentation\/SwiftPList\/PListArray"}],"type":"paragraph"}]],[[{"inlineContent":[{"type":"text","text":"dictionary"}],"type":"paragraph"}],[{"inlineContent":[{"type":"codeVoice","code":"["},{"text":" ","type":"text"},{"type":"codeVoice","code":"String:"},{"text":" ","type":"text"},{"isActive":true,"type":"reference","identifier":"doc:\/\/SwiftPList\/documentation\/SwiftPList\/PListValue"},{"text":" ","type":"text"},{"type":"codeVoice","code":"]"}],"type":"paragraph"}],[{"inlineContent":[{"isActive":true,"identifier":"doc:\/\/SwiftPList\/documentation\/SwiftPList\/PListDictionary","type":"reference"}],"type":"paragraph"}]],[[{"inlineContent":[{"type":"text","text":"string"}],"type":"paragraph"}],[{"inlineContent":[{"type":"codeVoice","code":"String"}],"type":"paragraph"}],[{"inlineContent":[{"text":"-","type":"text"}],"type":"paragraph"}]],[[{"inlineContent":[{"text":"data","type":"text"}],"type":"paragraph"}],[{"inlineContent":[{"code":"Data","type":"codeVoice"}],"type":"paragraph"}],[{"inlineContent":[{"type":"text","text":"-"}],"type":"paragraph"}]],[[{"inlineContent":[{"text":"date","type":"text"}],"type":"paragraph"}],[{"inlineContent":[{"type":"codeVoice","code":"Date"}],"type":"paragraph"}],[{"inlineContent":[{"type":"text","text":"-"}],"type":"paragraph"}]],[[{"inlineContent":[{"type":"text","text":"integer"}],"type":"paragraph"}],[{"inlineContent":[{"type":"codeVoice","code":"Int"}],"type":"paragraph"}],[{"inlineContent":[{"text":"-","type":"text"}],"type":"paragraph"}]],[[{"inlineContent":[{"type":"text","text":"float"}],"type":"paragraph"}],[{"inlineContent":[{"code":"Double","type":"codeVoice"}],"type":"paragraph"}],[{"inlineContent":[{"type":"text","text":"-"}],"type":"paragraph"}]],[[{"inlineContent":[{"type":"text","text":"boolean"}],"type":"paragraph"}],[{"inlineContent":[{"code":"Bool","type":"codeVoice"}],"type":"paragraph"}],[{"inlineContent":[{"type":"text","text":"-"}],"type":"paragraph"}]]],"type":"table"}]}],"metadata":{"roleHeading":"API Collection","modules":[{"name":"SwiftPList"}],"role":"collectionGroup","title":"Property List Value Types"},"seeAlsoSections":[{"title":"Guides","identifiers":["doc:\/\/SwiftPList\/documentation\/SwiftPList\/Create-a-new-plist","doc:\/\/SwiftPList\/documentation\/SwiftPList\/Load-a-plist-file-from-disk","doc:\/\/SwiftPList\/documentation\/SwiftPList\/Working-with-DictionaryPList","doc:\/\/SwiftPList\/documentation\/SwiftPList\/Working-with-Non-Dictionary-plists","doc:\/\/SwiftPList\/documentation\/SwiftPList\/Property-List-Formats"],"generated":true,"anchor":"Guides"}],"kind":"article","hierarchy":{"paths":[["doc:\/\/SwiftPList\/documentation\/SwiftPList"]]},"variants":[{"traits":[{"interfaceLanguage":"swift"}],"paths":["\/documentation\/swiftplist\/property-list-value-types"]}],"identifier":{"interfaceLanguage":"swift","url":"doc:\/\/SwiftPList\/documentation\/SwiftPList\/Property-List-Value-Types"},"abstract":[{"type":"text","text":"Valid property list value types."}],"schemaVersion":{"major":0,"patch":0,"minor":3},"references":{"doc://SwiftPList/documentation/SwiftPList/PList":{"title":"PList","kind":"symbol","type":"topic","role":"symbol","fragments":[{"text":"class","kind":"keyword"},{"text":" ","kind":"text"},{"text":"PList","kind":"identifier"}],"navigatorTitle":[{"text":"PList","kind":"identifier"}],"abstract":[{"type":"text","text":"Class representing a Property List (plist)."}],"url":"\/documentation\/swiftplist\/plist","identifier":"doc:\/\/SwiftPList\/documentation\/SwiftPList\/PList"},"doc://SwiftPList/documentation/SwiftPList/Working-with-Non-Dictionary-plists":{"kind":"article","url":"\/documentation\/swiftplist\/working-with-non-dictionary-plists","role":"collectionGroup","type":"topic","abstract":[{"type":"text","text":"An overview of working with non-Dictionary-rooted plists."}],"title":"Working with Non-Dictionary plists","identifier":"doc:\/\/SwiftPList\/documentation\/SwiftPList\/Working-with-Non-Dictionary-plists"},"doc://SwiftPList/documentation/SwiftPList/Create-a-new-plist":{"kind":"article","abstract":[{"text":"How to create a new empty plist object.","type":"text"}],"type":"topic","url":"\/documentation\/swiftplist\/create-a-new-plist","identifier":"doc:\/\/SwiftPList\/documentation\/SwiftPList\/Create-a-new-plist","title":"Create a New plist","role":"collectionGroup"},"doc://SwiftPList/documentation/SwiftPList/Working-with-DictionaryPList":{"identifier":"doc:\/\/SwiftPList\/documentation\/SwiftPList\/Working-with-DictionaryPList","kind":"article","role":"collectionGroup","title":"Working with DictionaryPList","type":"topic","url":"\/documentation\/swiftplist\/working-with-dictionaryplist","abstract":[{"text":"An overview of working with Dictionary-rooted plists.","type":"text"}]},"doc://SwiftPList/documentation/SwiftPList/PListValue":{"url":"\/documentation\/swiftplist\/plistvalue","type":"topic","kind":"symbol","abstract":[{"text":"Protocol representing all native Swift value types that property lists support, to facilitate","type":"text"},{"text":" ","type":"text"},{"text":"type safety and help prevent PList file save failure due to inadvertent use of incompatible","type":"text"},{"text":" ","type":"text"},{"text":"value types.","type":"text"}],"identifier":"doc:\/\/SwiftPList\/documentation\/SwiftPList\/PListValue","fragments":[{"text":"protocol","kind":"keyword"},{"text":" ","kind":"text"},{"text":"PListValue","kind":"identifier"}],"title":"PListValue","navigatorTitle":[{"text":"PListValue","kind":"identifier"}],"role":"symbol"},"https://developer.apple.com/library/archive/documentation/Cocoa/Conceptual/PropertyLists/AboutPropertyLists/AboutPropertyLists.html":{"title":"Property lists","identifier":"https:\/\/developer.apple.com\/library\/archive\/documentation\/Cocoa\/Conceptual\/PropertyLists\/AboutPropertyLists\/AboutPropertyLists.html","url":"https:\/\/developer.apple.com\/library\/archive\/documentation\/Cocoa\/Conceptual\/PropertyLists\/AboutPropertyLists\/AboutPropertyLists.html","type":"link","titleInlineContent":[{"type":"text","text":"Property lists"}]},"doc://SwiftPList/documentation/SwiftPList/Load-a-plist-file-from-disk":{"abstract":[{"type":"text","text":"Methods to load a .plist file from disk or from raw .plist file data."}],"url":"\/documentation\/swiftplist\/load-a-plist-file-from-disk","identifier":"doc:\/\/SwiftPList\/documentation\/SwiftPList\/Load-a-plist-file-from-disk","role":"collectionGroup","type":"topic","title":"Load a plist File From Disk","kind":"article"},"doc://SwiftPList/documentation/SwiftPList/PListArray":{"type":"topic","identifier":"doc:\/\/SwiftPList\/documentation\/SwiftPList\/PListArray","navigatorTitle":[{"kind":"identifier","text":"PListArray"}],"abstract":[{"type":"text","text":"Strongly-typed Array type used by "},{"type":"reference","identifier":"doc:\/\/SwiftPList\/documentation\/SwiftPList\/PList","isActive":true},{"type":"text","text":"."}],"title":"PListArray","kind":"symbol","role":"symbol","fragments":[{"kind":"keyword","text":"typealias"},{"kind":"text","text":" "},{"kind":"identifier","text":"PListArray"}],"url":"\/documentation\/swiftplist\/plistarray"},"doc://SwiftPList/documentation/SwiftPList/PListDictionary":{"fragments":[{"text":"typealias","kind":"keyword"},{"text":" ","kind":"text"},{"text":"PListDictionary","kind":"identifier"}],"navigatorTitle":[{"text":"PListDictionary","kind":"identifier"}],"title":"PListDictionary","identifier":"doc:\/\/SwiftPList\/documentation\/SwiftPList\/PListDictionary","abstract":[{"type":"text","text":"Strongly-typed Dictionary type used by "},{"type":"reference","isActive":true,"identifier":"doc:\/\/SwiftPList\/documentation\/SwiftPList\/PList"},{"type":"text","text":"."}],"kind":"symbol","url":"\/documentation\/swiftplist\/plistdictionary","type":"topic","role":"symbol"},"doc://SwiftPList/documentation/SwiftPList/Property-List-Formats":{"role":"collectionGroup","abstract":[{"type":"text","text":"Property list files can be encoded in different data formats."}],"type":"topic","title":"Property List Formats","url":"\/documentation\/swiftplist\/property-list-formats","kind":"article","identifier":"doc:\/\/SwiftPList\/documentation\/SwiftPList\/Property-List-Formats"},"doc://SwiftPList/documentation/SwiftPList":{"abstract":[{"type":"text","text":"A multi-platform Swift library bringing functional methods and type safety to .plist (Property List) files."}],"url":"\/documentation\/swiftplist","role":"collection","title":"SwiftPList","identifier":"doc:\/\/SwiftPList\/documentation\/SwiftPList","kind":"symbol","type":"topic"}}}